{
    "title": "ubuntu-test-unpacklinux",
    "last_modified": "2024-04-18 23:06:10",
    "description": "Intel Core i7-7500U testing with a Dell 0YNG98 (1.27.0 BIOS) and Intel HD 620 KBL GT2 3GB on Ubuntu 20.04 via the Phoronix Test Suite.",
    "systems": {
        "ubuntu-test-unpacklinux": {
            "identifier": "ubuntu-test-unpacklinux",
            "hardware": {
                "Processor": "Intel Core i7-7500U @ 3.50GHz (2 Cores \/ 4 Threads)",
                "Motherboard": "Dell 0YNG98 (1.27.0 BIOS)",
                "Chipset": "Intel Xeon E3-1200 v6\/7th",
                "Memory": "8GB",
                "Disk": "500GB Samsung SSD 860",
                "Graphics": "Intel HD 620 KBL GT2 3GB (1050MHz)",
                "Audio": "Realtek ALC3253",
                "Network": "Intel 3165"
            },
            "software": {
                "OS": "Ubuntu 20.04",
                "Kernel": "5.4.0-176-generic (x86_64)",
                "Desktop": "GNOME Shell 3.36.9",
                "Display Server": "X Server 1.20.13",
                "OpenGL": "4.6 Mesa 21.2.6",
                "Vulkan": "1.2.182",
                "Compiler": "GCC 9.4.0",
                "File-System": "ext4",
                "Screen Resolution": "1920x1080"
            },
            "user": "haris",
            "timestamp": "2024-04-18 23:04:46",
            "client_version": "10.8.4",
            "data": {
                "disk-scheduler": "MQ-DEADLINE",
                "disk-mount-options": "relatime,rw",
                "disk-details": "Block Size: 4096",
                "cpu-scaling-governor": "intel_pstate powersave (EPP: balance_performance)",
                "cpu-microcode": "0xf4",
                "cpu-thermald": "1.9.1",
                "kernel-extra-details": "Transparent Huge Pages: madvise",
                "environment-variables": "NVM_CD_FLAGS=",
                "security": "gather_data_sampling: Mitigation of Microcode + itlb_multihit: KVM: Mitigation of Split huge pages + l1tf: Mitigation of PTE Inversion; VMX: conditional cache flushes SMT vulnerable + mds: Mitigation of Clear buffers; SMT vulnerable + meltdown: Mitigation of PTI + mmio_stale_data: Mitigation of Clear buffers; SMT vulnerable + retbleed: Mitigation of IBRS + spec_store_bypass: Mitigation of SSB disabled via prctl and seccomp + spectre_v1: Mitigation of usercopy\/swapgs barriers and __user pointer sanitization + spectre_v2: Mitigation of IBRS IBPB: conditional STIBP: conditional RSB filling PBRSB-eIBRS: Not affected + srbds: Mitigation of Microcode + tsx_async_abort: Not affected"
            }
        }
    },
    "results": {
        "4aeeef0c03d9ac8f35fdf1c10745d11a5c0bfe75": {
            "identifier": "pts\/unpack-linux-1.2.0",
            "title": "Unpacking The Linux Kernel",
            "app_version": "5.19",
            "description": "linux-5.19.tar.xz",
            "scale": "Seconds",
            "proportion": "LIB",
            "display_format": "BAR_GRAPH",
            "results": {
                "ubuntu-test-unpacklinux": {
                    "value": 12.7810000000000005826450433232821524143218994140625,
                    "raw_values": [
                        12.574999999999999289457264239899814128875732421875,
                        12.6699999999999999289457264239899814128875732421875,
                        12.9909999999999996589394868351519107818603515625,
                        12.888999999999999346300683100707828998565673828125
                    ],
                    "test_run_times": [
                        12.5800000000000000710542735760100185871124267578125,
                        12.6699999999999999289457264239899814128875732421875,
                        12.9900000000000002131628207280300557613372802734375,
                        12.8900000000000005684341886080801486968994140625
                    ]
                }
            }
        }
    }
}